Workbook

Sheet Dashboard
A1: Sales Performance Dashboard
A2: FY2025 | 1,500 synthetic orders generated for portfolio demonstration - not real company data. Revenue = Units x Unit Price x (1 - Discount); Profit = Revenue - Units x Unit Cost.
A4: Total revenue | B4: Total profit | C4: Profit margin | D4: Orders | F4: Top region | G4: Avg order value | H4: Units sold | I4: Top product
A5: =SUM(Data!$K$2:$K$1501) -> 824816.3 | B5: =SUM(Data!$M$2:$M$1501) -> 237857.8 | C5: =IFERROR(B5/A5,0) -> 0.2883767 | D5: =COUNTA(Data!$A$2:$A$1501) -> 1500 | F5: =INDEX(F40:F43,MATCH(MAX(G40:G43),G40:G43,0)) -> West | G5: =IFERROR(A5/D5,0) -> 549.87753 | H5: =SUM(Data!$G$2:$G$1501) -> 22609 | I5: =INDEX(F62:F70,MATCH(MAX(G62:G70),G62:G70,0)) -> Smartphone
A38: Monthly performance | F38: By region
A39: Month | B39: Revenue | C39: Profit | D39: Margin | F39: Region | G39: Revenue | H39: Profit | I39: Margin
A40: Jan | B40: =SUMIFS(Data!$K$2:$K$1501,Data!$N$2:$N$1501,$A40) -> 61583.35 | C40: =SUMIFS(Data!$M$2:$M$1501,Data!$N$2:$N$1501,$A40) -> 16838.85 | D40: =IFERROR(C40/B40,0) -> 0.27343186 | F40: West | G40: =SUMIFS(Data!$K$2:$K$1501,Data!$C$2:$C$1501,$F40) -> 257674.25 | H40: =SUMIFS(Data!$M$2:$M$1501,Data!$C$2:$C$1501,$F40) -> 71414.75 | I40: =IFERROR(H40/G40,0) -> 0.27715129
A41: Feb | B41: =SUMIFS(Data!$K$2:$K$1501,Data!$N$2:$N$1501,$A41) -> 46425.65 | C41: =SUMIFS(Data!$M$2:$M$1501,Data!$N$2:$N$1501,$A41) -> 13985.65 | D41: =IFERROR(C41/B41,0) -> 0.30124834 | F41: North | G41: =SUMIFS(Data!$K$2:$K$1501,Data!$C$2:$C$1501,$F41) -> 237399.7 | H41: =SUMIFS(Data!$M$2:$M$1501,Data!$C$2:$C$1501,$F41) -> 70377.2 | I41: =IFERROR(H41/G41,0) -> 0.29645025
A42: Mar | B42: =SUMIFS(Data!$K$2:$K$1501,Data!$N$2:$N$1501,$A42) -> 62138.65 | C42: =SUMIFS(Data!$M$2:$M$1501,Data!$N$2:$N$1501,$A42) -> 16960.65 | D42: =IFERROR(C42/B42,0) -> 0.27294848 | F42: South | G42: =SUMIFS(Data!$K$2:$K$1501,Data!$C$2:$C$1501,$F42) -> 191091.85 | H42: =SUMIFS(Data!$M$2:$M$1501,Data!$C$2:$C$1501,$F42) -> 56034.85 | I42: =IFERROR(H42/G42,0) -> 0.29323516
A43: Apr | B43: =SUMIFS(Data!$K$2:$K$1501,Data!$N$2:$N$1501,$A43) -> 60172.55 | C43: =SUMIFS(Data!$M$2:$M$1501,Data!$N$2:$N$1501,$A43) -> 16779.05 | D43: =IFERROR(C43/B43,0) -> 0.27884891 | F43: East | G43: =SUMIFS(Data!$K$2:$K$1501,Data!$C$2:$C$1501,$F43) -> 138650.5 | H43: =SUMIFS(Data!$M$2:$M$1501,Data!$C$2:$C$1501,$F43) -> 40031 | I43: =IFERROR(H43/G43,0) -> 0.28871876
A44: May | B44: =SUMIFS(Data!$K$2:$K$1501,Data!$N$2:$N$1501,$A44) -> 61557.6 | C44: =SUMIFS(Data!$M$2:$M$1501,Data!$N$2:$N$1501,$A44) -> 19287.6 | D44: =IFERROR(C44/B44,0) -> 0.31332606 | F44: Total | G44: =SUM(G40:G43) -> 824816.3 | H44: =SUM(H40:H43) -> 237857.8 | I44: =IFERROR(H44/G44,0) -> 0.2883767
A45: Jun | B45: =SUMIFS(Data!$K$2:$K$1501,Data!$N$2:$N$1501,$A45) -> 59143.45 | C45: =SUMIFS(Data!$M$2:$M$1501,Data!$N$2:$N$1501,$A45) -> 18183.45 | D45: =IFERROR(C45/B45,0) -> 0.30744656
A46: Jul | B46: =SUMIFS(Data!$K$2:$K$1501,Data!$N$2:$N$1501,$A46) -> 64514.65 | C46: =SUMIFS(Data!$M$2:$M$1501,Data!$N$2:$N$1501,$A46) -> 20289.65 | D46: =IFERROR(C46/B46,0) -> 0.31449678 | F46: By category
A47: Aug | B47: =SUMIFS(Data!$K$2:$K$1501,Data!$N$2:$N$1501,$A47) -> 64541.75 | C47: =SUMIFS(Data!$M$2:$M$1501,Data!$N$2:$N$1501,$A47) -> 18173.25 | D47: =IFERROR(C47/B47,0) -> 0.28157356 | F47: Category | G47: Revenue | H47: Profit | I47: Margin
A48: Sep | B48: =SUMIFS(Data!$K$2:$K$1501,Data!$N$2:$N$1501,$A48) -> 91449 | C48: =SUMIFS(Data!$M$2:$M$1501,Data!$N$2:$N$1501,$A48) -> 23823 | D48: =IFERROR(C48/B48,0) -> 0.26050586 | F48: Electronics | G48: =SUMIFS(Data!$K$2:$K$1501,Data!$D$2:$D$1501,$F48) -> 404850 | H48: =SUMIFS(Data!$M$2:$M$1501,Data!$D$2:$D$1501,$F48) -> 76084 | I48: =IFERROR(H48/G48,0) -> 0.18793133
A49: Oct | B49: =SUMIFS(Data!$K$2:$K$1501,Data!$N$2:$N$1501,$A49) -> 64704.9 | C49: =SUMIFS(Data!$M$2:$M$1501,Data!$N$2:$N$1501,$A49) -> 20128.9 | D49: =IFERROR(C49/B49,0) -> 0.31108772 | F49: Furniture | G49: =SUMIFS(Data!$K$2:$K$1501,Data!$D$2:$D$1501,$F49) -> 122213.5 | H49: =SUMIFS(Data!$M$2:$M$1501,Data!$D$2:$D$1501,$F49) -> 47988.5 | I49: =IFERROR(H49/G49,0) -> 0.3926612
A50: Nov | B50: =SUMIFS(Data!$K$2:$K$1501,Data!$N$2:$N$1501,$A50) -> 95169.55 | C50: =SUMIFS(Data!$M$2:$M$1501,Data!$N$2:$N$1501,$A50) -> 26831.05 | D50: =IFERROR(C50/B50,0) -> 0.28192894 | F50: Office Supplies | G50: =SUMIFS(Data!$K$2:$K$1501,Data!$D$2:$D$1501,$F50) -> 297752.8 | H50: =SUMIFS(Data!$M$2:$M$1501,Data!$D$2:$D$1501,$F50) -> 113785.3 | I50: =IFERROR(H50/G50,0) -> 0.38214687
A51: Dec | B51: =SUMIFS(Data!$K$2:$K$1501,Data!$N$2:$N$1501,$A51) -> 93415.2 | C51: =SUMIFS(Data!$M$2:$M$1501,Data!$N$2:$N$1501,$A51) -> 26576.7 | D51: =IFERROR(C51/B51,0) -> 0.28450081 | F51: Total | G51: =SUM(G48:G50) -> 824816.3 | H51: =SUM(H48:H50) -> 237857.8 | I51: =IFERROR(H51/G51,0) -> 0.2883767
A52: Total | B52: =SUM(B40:B51) -> 824816.3 | C52: =SUM(C40:C51) -> 237857.8 | D52: =IFERROR(C52/B52,0) -> 0.2883767
F53: By channel
F54: Channel | G54: Revenue | H54: Profit | I54: Margin
A55: Discount impact on margin | F55: Online | G55: =SUMIFS(Data!$K$2:$K$1501,Data!$F$2:$F$1501,$F55) -> 345959.15 | H55: =SUMIFS(Data!$M$2:$M$1501,Data!$F$2:$F$1501,$F55) -> 98582.65 | I55: =IFERROR(H55/G55,0) -> 0.2849546
A56: Discount | B56: Orders | C56: Revenue | D56: Margin | F56: Retail | G56: =SUMIFS(Data!$K$2:$K$1501,Data!$F$2:$F$1501,$F56) -> 257789.65 | H56: =SUMIFS(Data!$M$2:$M$1501,Data!$F$2:$F$1501,$F56) -> 79574.65 | I56: =IFERROR(H56/G56,0) -> 0.30868055
A57: 0 | B57: =COUNTIFS(Data!$J$2:$J$1501,$A57) -> 459 | C57: =SUMIFS(Data!$K$2:$K$1501,Data!$J$2:$J$1501,$A57) -> 241782 | D57: =IFERROR(SUMIFS(Data!$M$2:$M$1501,Data!$J$2:$J$1501,$A57)/C57,0) -> 0.33355254 | F57: Distributor | G57: =SUMIFS(Data!$K$2:$K$1501,Data!$F$2:$F$1501,$F57) -> 221067.5 | H57: =SUMIFS(Data!$M$2:$M$1501,Data!$F$2:$F$1501,$F57) -> 59700.5 | I57: =IFERROR(H57/G57,0) -> 0.27005553
A58: 0.05 | B58: =COUNTIFS(Data!$J$2:$J$1501,$A58) -> 370 | C58: =SUMIFS(Data!$K$2:$K$1501,Data!$J$2:$J$1501,$A58) -> 180005.05 | D58: =IFERROR(SUMIFS(Data!$M$2:$M$1501,Data!$J$2:$J$1501,$A58)/C58,0) -> 0.29322816 | F58: Total | G58: =SUM(G55:G57) -> 824816.3 | H58: =SUM(H55:H57) -> 237857.8 | I58: =IFERROR(H58/G58,0) -> 0.2883767
A59: 0.1 | B59: =COUNTIFS(Data!$J$2:$J$1501,$A59) -> 376 | C59: =SUMIFS(Data!$K$2:$K$1501,Data!$J$2:$J$1501,$A59) -> 206964.9 | D59: =IFERROR(SUMIFS(Data!$M$2:$M$1501,Data!$J$2:$J$1501,$A59)/C59,0) -> 0.27116385
A60: 0.15 | B60: =COUNTIFS(Data!$J$2:$J$1501,$A60) -> 217 | C60: =SUMIFS(Data!$K$2:$K$1501,Data!$J$2:$J$1501,$A60) -> 136427.55 | D60: =IFERROR(SUMIFS(Data!$M$2:$M$1501,Data!$J$2:$J$1501,$A60)/C60,0) -> 0.26364946 | F60: By product
A61: 0.2 | B61: =COUNTIFS(Data!$J$2:$J$1501,$A61) -> 78 | C61: =SUMIFS(Data!$K$2:$K$1501,Data!$J$2:$J$1501,$A61) -> 59636.8 | D61: =IFERROR(SUMIFS(Data!$M$2:$M$1501,Data!$J$2:$J$1501,$A61)/C61,0) -> 0.20688233 | F61: Product | G61: Revenue | H61: Profit | I61: Margin
F62: Smartphone | G62: =SUMIFS(Data!$K$2:$K$1501,Data!$E$2:$E$1501,$F62) -> 176202 | H62: =SUMIFS(Data!$M$2:$M$1501,Data!$E$2:$E$1501,$F62) -> 25972 | I62: =IFERROR(H62/G62,0) -> 0.14739901
F63: Printer Paper (carton) | G63: =SUMIFS(Data!$K$2:$K$1501,Data!$E$2:$E$1501,$F63) -> 167255.2 | H63: =SUMIFS(Data!$M$2:$M$1501,Data!$E$2:$E$1501,$F63) -> 54647.2 | I63: =IFERROR(H63/G63,0) -> 0.32672945
F64: Laptop | G64: =SUMIFS(Data!$K$2:$K$1501,Data!$E$2:$E$1501,$F64) -> 139386 | H64: =SUMIFS(Data!$M$2:$M$1501,Data!$E$2:$E$1501,$F64) -> 24186 | I64: =IFERROR(H64/G64,0) -> 0.17351814
F65: Headphones | G65: =SUMIFS(Data!$K$2:$K$1501,Data!$E$2:$E$1501,$F65) -> 89262 | H65: =SUMIFS(Data!$M$2:$M$1501,Data!$E$2:$E$1501,$F65) -> 25926 | I65: =IFERROR(H65/G65,0) -> 0.29044834
F66: Notebook Pack | G66: =SUMIFS(Data!$K$2:$K$1501,Data!$E$2:$E$1501,$F66) -> 75797.4 | H66: =SUMIFS(Data!$M$2:$M$1501,Data!$E$2:$E$1501,$F66) -> 34691.4 | I66: =IFERROR(H66/G66,0) -> 0.45768588
F67: Pen Set | G67: =SUMIFS(Data!$K$2:$K$1501,Data!$E$2:$E$1501,$F67) -> 54700.2 | H67: =SUMIFS(Data!$M$2:$M$1501,Data!$E$2:$E$1501,$F67) -> 24446.7 | I67: =IFERROR(H67/G67,0) -> 0.44692158
F68: Standing Desk | G68: =SUMIFS(Data!$K$2:$K$1501,Data!$E$2:$E$1501,$F68) -> 49024 | H68: =SUMIFS(Data!$M$2:$M$1501,Data!$E$2:$E$1501,$F68) -> 18499 | I68: =IFERROR(H68/G68,0) -> 0.37734579
F69: Office Chair | G69: =SUMIFS(Data!$K$2:$K$1501,Data!$E$2:$E$1501,$F69) -> 45585 | H69: =SUMIFS(Data!$M$2:$M$1501,Data!$E$2:$E$1501,$F69) -> 18935 | I69: =IFERROR(H69/G69,0) -> 0.41537787
F70: Bookshelf | G70: =SUMIFS(Data!$K$2:$K$1501,Data!$E$2:$E$1501,$F70) -> 27604.5 | H70: =SUMIFS(Data!$M$2:$M$1501,Data!$E$2:$E$1501,$F70) -> 10554.5 | I70: =IFERROR(H70/G70,0) -> 0.38234708
F71: Total | G71: =SUM(G62:G70) -> 824816.3 | H71: =SUM(H62:H70) -> 237857.8 | I71: =IFERROR(H71/G71,0) -> 0.2883767

Sheet Data
A1: Order ID | B1: Order Date | C1: Region | D1: Category | E1: Product | F1: Channel | G1: Units | H1: Unit Price | I1: Unit Cost | J1: Discount | K1: Revenue | L1: Cost | M1: Profit | N1: Month
A2: ORD-0001 | B2: 45658 | C2: North | D2: Electronics | E2: Smartphone | F2: Retail | G2: 1 | H2: 520 | I2: 415 | J2: 0 | K2: =G2*H2*(1-J2) -> 520 | L2: =G2*I2 -> 415 | M2: =K2-L2 -> 105 | N2: =TEXT(B2,"mmm") -> Jan
A3: ORD-0002 | B3: 45658 | C3: North | D3: Electronics | E3: Laptop | F3: Online | G3: 3 | H3: 780 | I3: 600 | J3: 0.05 | K3: =G3*H3*(1-J3) -> 2223 | L3: =G3*I3 -> 1800 | M3: =K3-L3 -> 423 | N3: =TEXT(B3,"mmm") -> Jan
A4: ORD-0003 | B4: 45658 | C4: West | D4: Electronics | E4: Smartphone | F4: Online | G4: 3 | H4: 520 | I4: 415 | J4: 0.05 | K4: =G4*H4*(1-J4) -> 1482 | L4: =G4*I4 -> 1245 | M4: =K4-L4 -> 237 | N4: =TEXT(B4,"mmm") -> Jan
A5: ORD-0004 | B5: 45658 | C5: South | D5: Electronics | E5: Headphones | F5: Distributor | G5: 18 | H5: 90 | I5: 58 | J5: 0.15 | K5: =G5*H5*(1-J5) -> 1377 | L5: =G5*I5 -> 1044 | M5: =K5-L5 -> 333 | N5: =TEXT(B5,"mmm") -> Jan
A6: ORD-0005 | B6: 45658 | C6: South | D6: Furniture | E6: Office Chair | F6: Online | G6: 1 | H6: 150 | I6: 82 | J6: 0.05 | K6: =G6*H6*(1-J6) -> 142.5 | L6: =G6*I6 -> 82 | M6: =K6-L6 -> 60.5 | N6: =TEXT(B6,"mmm") -> Jan
A7: ORD-0006 | B7: 45659 | C7: North | D7: Electronics | E7: Smartphone | F7: Retail | G7: 4 | H7: 520 | I7: 415 | J7: 0 | K7: =G7*H7*(1-J7) -> 2080 | L7: =G7*I7 -> 1660 | M7: =K7-L7 -> 420 | N7: =TEXT(B7,"mmm") -> Jan
A8: ORD-0007 | B8: 45659 | C8: East | D8: Electronics | E8: Headphones | F8: Retail | G8: 2 | H8: 90 | I8: 58 | J8: 0.05 | K8: =G8*H8*(1-J8) -> 171 | L8: =G8*I8 -> 116 | M8: =K8-L8 -> 55 | N8: =TEXT(B8,"mmm") -> Jan
A9: ORD-0008 | B9: 45659 | C9: North | D9: Electronics | E9: Smartphone | F9: Online | G9: 1 | H9: 520 | I9: 415 | J9: 0.05 | K9: =G9*H9*(1-J9) -> 494 | L9: =G9*I9 -> 415 | M9: =K9-L9 -> 79 | N9: =TEXT(B9,"mmm") -> Jan
A10: ORD-0009 | B10: 45659 | C10: North | D10: Office Supplies | E10: Notebook Pack | F10: Distributor | G10: 27 | H10: 12 | I10: 6 | J10: 0.1 | K10: =G10*H10*(1-J10) -> 291.6 | L10: =G10*I10 -> 162 | M10: =K10-L10 -> 129.6 | N10: =TEXT(B10,"mmm") -> Jan
A11: ORD-0010 | B11: 45659 | C11: North | D11: Office Supplies | E11: Printer Paper (carton) | F11: Online | G11: 18 | H11: 28 | I11: 17 | J11: 0 | K11: =G11*H11*(1-J11) -> 504 | L11: =G11*I11 -> 306 | M11: =K11-L11 -> 198 | N11: =TEXT(B11,"mmm") -> Jan
A12: ORD-0011 | B12: 45660 | C12: West | D12: Electronics | E12: Headphones | F12: Retail | G12: 2 | H12: 90 | I12: 58 | J12: 0.05 | K12: =G12*H12*(1-J12) -> 171 | L12: =G12*I12 -> 116 | M12: =K12-L12 -> 55 | N12: =TEXT(B12,"mmm") -> Jan
A13: ORD-0012 | B13: 45660 | C13: West | D13: Electronics | E13: Smartphone | F13: Online | G13: 4 | H13: 520 | I13: 415 | J13: 0 | K13: =G13*H13*(1-J13) -> 2080 | L13: =G13*I13 -> 1660 | M13: =K13-L13 -> 420 | N13: =TEXT(B13,"mmm") -> Jan
... A1501: ORD-1500 | B1501: 46019 | C1501: West | D1501: Office Supplies | E1501: Notebook Pack | F1501: Retail | G1501: 23 | H1501: 12 | I1501: 6 | J1501: 0.1 | K1501: =G1501*H1501*(1-J1501) -> 248.4 | L1501: =G1501*I1501 -> 138 | M1501: =K1501-L1501 -> 110.4 | N1501: =TEXT(B1501,"mmm") -> Dec
